utils_plus/__init__.py
utils_plus/abstracts.py
utils_plus/apps.py
utils_plus/choices.py
utils_plus/fields.py
utils_plus/management/__init__.py
utils_plus/management/commands/__init__.py
utils_plus/management/commands/clear_records.py
utils_plus/management/commands/cleardata.py
utils_plus/management/commands/create_admin.py
utils_plus/management/commands/create_middleware.py
utils_plus/management/commands/test_mail.py
utils_plus/middleware.py
utils_plus/migrations/__init__.py
utils_plus/mixins.py
utils_plus/models.py
utils_plus/router.py
utils_plus/templatetags/__init__.py
utils_plus/templatetags/utils_plus_tags.py
utils_plus/utils/__init__.py
utils_plus/utils/html.py
utils_plus/utils/misc.py
utils_plus/utils/npm.py
utils_plus/views/__init__.py
utils_plus/views/misc.py
utils_plus/views/multi_form_view.py
django_utils_plus-0.7.6.dist-info/WHEEL
django_utils_plus-0.7.6.dist-info/METADATA
django_utils_plus-0.7.6.dist-info/licenses/LICENSE
django_utils_plus-0.7.6.dist-info/RECORD
