Metadata-Version: 2.1
Name: django-utils-plus
Version: 0.7.6
Summary: A reusable Django app with small set of utilities for urls, viewsets, commands and more
License: MIT
Author-email: jnoortheen <jnoortheen@gmail.com>
Requires-Python: >=3.8
Classifier: Environment :: Web Environment
Classifier: Framework :: Django
Classifier: Intended Audience :: Developers
Classifier: License :: OSI Approved :: MIT License
Classifier: Natural Language :: English
Classifier: Operating System :: OS Independent
Classifier: Programming Language :: Python
Classifier: Programming Language :: Python :: 3
Classifier: Topic :: Internet :: WWW/HTTP
Classifier: Topic :: Internet :: WWW/HTTP :: Dynamic Content
Classifier: Topic :: Software Development :: Libraries
Classifier: Topic :: Software Development :: Libraries :: Python Modules
Classifier: Topic :: Utilities
Requires-Dist: django>=4.2
Provides-Extra: lint
Requires-Dist: django-stubs; extra == "lint"
Requires-Dist: mypy; extra == "lint"
Requires-Dist: ruff; extra == "lint"
Provides-Extra: test
Requires-Dist: pytest-django; extra == "test"
Requires-Dist: pytest-cov; extra == "test"
Requires-Dist: django_dynamic_fixture; extra == "test"
Project-URL: homepage, https://github.com/jnoortheen/django-utils-plus
Project-URL: repository, https://github.com/jnoortheen/django-utils-plus
